simple_tsp/__init__.py
simple_tsp/py.typed
simple_tsp/tsp.py
simple_tsp-0.2.1.dist-info/WHEEL
simple_tsp-0.2.1.dist-info/METADATA
simple_tsp-0.2.1.dist-info/RECORD
