Metadata-Version: 2.3
Name: simple-tsp
Version: 0.2.1
Summary: Solving the Traveling Salesman Problem
Author: Saito Tsutomu
Author-email: Saito Tsutomu <tsutomu7@hotmail.co.jp>
Classifier: Development Status :: 1 - Planning
Classifier: License :: OSI Approved :: Apache Software License
Classifier: Programming Language :: Python
Classifier: Topic :: Software Development
Classifier: Topic :: Scientific/Engineering
Requires-Dist: pyvrp>=0.12.1
Requires-Python: >=3.12
Project-URL: homepage, https://github.com/SaitoTsutomu/simple-tsp
